mumu_notion/__init__.py
mumu_notion/api_endpoints.py
mumu_notion/client.py
mumu_notion/errors.py
mumu_notion/py.typed
mumu_notion/utils.py
mumu_notion/validation_tools.py
tests/__init__.py
tests/constants.py
tests/helpers.py
tests/test_api_exceptions.py
tests/test_clients.py
tests/test_example_codes.py
tests/test_util_functions.py
tests/test_validation_tools.py
mumu_notion-0.0.3.dist-info/LICENSE
mumu_notion-0.0.3.dist-info/METADATA
mumu_notion-0.0.3.dist-info/WHEEL
mumu_notion-0.0.3.dist-info/top_level.txt
mumu_notion-0.0.3.dist-info/RECORD
